csdid/__init__.py
csdid/_version.py
csdid/att_gt.py
csdid/aggte_fnc/__init__.py
csdid/aggte_fnc/aggte.py
csdid/aggte_fnc/compute_aggte.py
csdid/aggte_fnc/utils.py
csdid/attgt_fnc/__init__.py
csdid/attgt_fnc/compute_att_gt.py
csdid/attgt_fnc/preprocess_did.py
csdid/plots/__init__.py
csdid/plots/gplot.py
csdid/utils/__init__.py
csdid/utils/bmisc.py
csdid/utils/mboot.py
csdid-0.2.9.dist-info/licenses/LICENSE
csdid-0.2.9.dist-info/METADATA
csdid-0.2.9.dist-info/WHEEL
csdid-0.2.9.dist-info/top_level.txt
csdid-0.2.9.dist-info/RECORD
